viewrouter/__init__.py
viewrouter/routers.py
viewrouter/templates/viewrouter/actionview_index.html
viewrouter/tests.py
viewrouter/views.py
django_viewrouter-0.1.3.dist-info/METADATA
django_viewrouter-0.1.3.dist-info/WHEEL
django_viewrouter-0.1.3.dist-info/RECORD
