Metadata-Version: 2.1
Name: django-viewrouter
Version: 0.1.3
Summary: 
License: MIT
Author: Kamal Mustafa
Author-email: k4ml@github.io
Requires-Python: >=3.10,<4.0
Classifier: License :: OSI Approved :: MIT License
Classifier: Programming Language :: Python :: 3
Classifier: Programming Language :: Python :: 3.10
Classifier: Programming Language :: Python :: 3.11
Requires-Dist: Django (>=3.0)
